finary_uapi/CONTRIBUTING.md
finary_uapi/__init__.py
finary_uapi/__main__.py
finary_uapi/auth.py
finary_uapi/bank_account_types.py
finary_uapi/constants.py
finary_uapi/crypto_chains.py
finary_uapi/currencies.py
finary_uapi/generic_asset_categories.py
finary_uapi/importers/crowdlending_generic_csv.py
finary_uapi/importers/crypto_generic_csv.py
finary_uapi/importers/cryptocom.py
finary_uapi/importers/nexo.py
finary_uapi/importers/stocks_generic_csv.py
finary_uapi/institutions.py
finary_uapi/precious_metals.py
finary_uapi/real_estates.py
finary_uapi/scpis.py
finary_uapi/securities.py
finary_uapi/signin.py
finary_uapi/user_crowdlendings.py
finary_uapi/user_cryptos.py
finary_uapi/user_fonds_euro.py
finary_uapi/user_generic_assets.py
finary_uapi/user_holdings_accounts.py
finary_uapi/user_me.py
finary_uapi/user_portfolio.py
finary_uapi/user_precious_metals.py
finary_uapi/user_real_estates.py
finary_uapi/user_scpis.py
finary_uapi/user_securities.py
finary_uapi/user_startups.py
finary_uapi/utils.py
finary_uapi/views.py
finary_uapi/watches.py
finary_uapi-0.2.1.dist-info/LICENSE
finary_uapi-0.2.1.dist-info/METADATA
finary_uapi-0.2.1.dist-info/WHEEL
finary_uapi-0.2.1.dist-info/RECORD
