Metadata-Version: 2.1
Name: finary-uapi
Version: 0.2.1
Summary: Finary API client and command line tool to interact with your Finary account.
License: MIT
Author: lasconic
Author-email: lasconic@gmail.com
Requires-Python: >=3.10,<4.0
Classifier: License :: OSI Approved :: MIT License
Classifier: Programming Language :: Python :: 3
Classifier: Programming Language :: Python :: 3.10
Classifier: Programming Language :: Python :: 3.11
Classifier: Programming Language :: Python :: 3.12
Requires-Dist: docopt (>=0.6.2,<0.7.0)
Requires-Dist: fuzzywuzzy[speedup] (>=0.18.0,<0.19.0)
Requires-Dist: requests (>=2.32.3,<3.0.0)
